tno/mpc/encryption_schemes/templates/__init__.py
tno/mpc/encryption_schemes/templates/_randomness_manager.py
tno/mpc/encryption_schemes/templates/asymmetric_encryption_scheme.py
tno/mpc/encryption_schemes/templates/encryption_scheme.py
tno/mpc/encryption_schemes/templates/exceptions.py
tno/mpc/encryption_schemes/templates/homomorphic_encryption_scheme.py
tno/mpc/encryption_schemes/templates/py.typed
tno/mpc/encryption_schemes/templates/randomized_encryption_scheme.py
tno/mpc/encryption_schemes/templates/random_sources/__init__.py
tno/mpc/encryption_schemes/templates/random_sources/contextless_source.py
tno/mpc/encryption_schemes/templates/random_sources/file_source.py
tno/mpc/encryption_schemes/templates/random_sources/process_source.py
tno/mpc/encryption_schemes/templates/test/__init__.py
tno/mpc/encryption_schemes/templates/test/conftest.py
tno/mpc/encryption_schemes/templates/test/pytest_plugins.py
tno/mpc/encryption_schemes/templates/test/test_homomorphic_encryption_scheme.py
tno/mpc/encryption_schemes/templates/test/test_randomized_encryption_scheme.py
tno/mpc/encryption_schemes/templates/test/test_randomness_manager.py
tno/mpc/encryption_schemes/templates/test/test_scheme_management.py
tno/mpc/encryption_schemes/templates/test/random_sources/__init__.py
tno/mpc/encryption_schemes/templates/test/random_sources/numbers_sep_comma.txt
tno/mpc/encryption_schemes/templates/test/random_sources/numbers_sep_newline.txt
tno/mpc/encryption_schemes/templates/test/random_sources/test_contextless_source.py
tno/mpc/encryption_schemes/templates/test/random_sources/test_file_source.py
tno/mpc/encryption_schemes/templates/test/random_sources/test_process_source.py
tno/mpc/encryption_schemes/templates/util/__init__.py
tno/mpc/encryption_schemes/templates/util/instance_manager.py
tno_mpc_encryption_schemes_templates-5.0.0.dist-info/licenses/LICENSE
tno_mpc_encryption_schemes_templates-5.0.0.dist-info/METADATA
tno_mpc_encryption_schemes_templates-5.0.0.dist-info/WHEEL
tno_mpc_encryption_schemes_templates-5.0.0.dist-info/entry_points.txt
tno_mpc_encryption_schemes_templates-5.0.0.dist-info/top_level.txt
tno_mpc_encryption_schemes_templates-5.0.0.dist-info/RECORD
