Metadata-Version: 2.4
Name: tno.mpc.encryption_schemes.templates
Version: 5.0.0
Summary: Generic templates for different types of Encryption Schemes
Author-email: TNO PET Lab <petlab@tno.nl>
Maintainer-email: TNO PET Lab <petlab@tno.nl>
License: Apache License, Version 2.0
Project-URL: Homepage, https://pet.tno.nl/
Project-URL: Documentation, https://docs.pet.tno.nl/mpc/encryption_schemes/templates/5.0.0
Project-URL: Source, https://github.com/TNO-MPC/encryption_schemes.templates
Keywords: TNO,MPC,multi-party computation,encryption schemes,templates
Platform: any
Classifier: License :: OSI Approved :: Apache Software License
Classifier: Programming Language :: Python :: 3
Classifier: Operating System :: OS Independent
Classifier: Intended Audience :: Developers
Classifier: Intended Audience :: Information Technology
Classifier: Intended Audience :: Science/Research
Classifier: Typing :: Typed
Classifier: Topic :: Security :: Cryptography
Requires-Python: >=3.9
License-File: LICENSE
Requires-Dist: tenacity
Requires-Dist: typing_extensions~=4.0; python_version < "3.11"
Provides-Extra: tests
Requires-Dist: pytest>=8.1; extra == "tests"
Requires-Dist: pytest-timeout; extra == "tests"
Dynamic: license-file
